{"box_data": [{"position": {"minX": 639.5, "minY": 266.25, "maxX": 657.5, "maxY": 323.75}, "class_id": 0, "box_caption": "Sorrel 0.066", "scores": {"class_score": 0.06585693359375}, "domain": "pixel"}, {"position": {"minX": 663.0, "minY": 350.5, "maxX": 672.0, "maxY": 382.0}, "class_id": 0, "box_caption": "Sorrel 0.001", "scores": {"class_score": 0.0013885498046875}, "domain": "pixel"}, {"position": {"minX": 663.0, "minY": 362.0, "maxX": 673.0, "maxY": 383.0}, "class_id": 0, "box_caption": "Sorrel 0.001", "scores": {"class_score": 0.0014667510986328125}, "domain": "pixel"}, {"position": {"minX": 662.5, "minY": 371.25, "maxX": 672.5, "maxY": 385.25}, "class_id": 0, "box_caption": "Sorrel 0.001", "scores": {"class_score": 0.0011653900146484375}, "domain": "pixel"}, {"position": {"minX": 655.0, "minY": 350.25, "maxX": 673.0, "maxY": 381.75}, "class_id": 0, "box_caption": "Sorrel 0.001", "scores": {"class_score": 0.0011157989501953125}, "domain": "pixel"}, {"position": {"minX": 614.0, "minY": 60.15625, "maxX": 656.0, "maxY": 138.875}, "class_id": 0, "box_caption": "Sorrel 0.003", "scores": {"class_score": 0.00323486328125}, "domain": "pixel"}, {"position": {"minX": 637.0, "minY": 278.0, "maxX": 655.0, "maxY": 326.0}, "class_id": 0, "box_caption": "Sorrel 0.008", "scores": {"class_score": 0.0082550048828125}, "domain": "pixel"}, {"position": {"minX": 633.0, "minY": 256.5, "maxX": 655.0, "maxY": 323.0}, "class_id": 0, "box_caption": "Sorrel 0.001", "scores": {"class_score": 0.0013456344604492188}, "domain": "pixel"}, {"position": {"minX": 547.0, "minY": 155.0, "maxX": 599.0, "maxY": 195.75}, "class_id": 0, "box_caption": "Sorrel 0.283", "scores": {"class_score": 0.283447265625}, "domain": "pixel"}, {"position": {"minX": 549.0, "minY": 154.0, "maxX": 584.0, "maxY": 191.5}, "class_id": 0, "box_caption": "Sorrel 0.001", "scores": {"class_score": 0.0010080337524414062}, "domain": "pixel"}, {"position": {"minX": 368.75, "minY": 193.875, "maxX": 524.5, "maxY": 340.0}, "class_id": 0, "box_caption": "Sorrel 0.006", "scores": {"class_score": 0.00586700439453125}, "domain": "pixel"}, {"position": {"minX": 205.25, "minY": 73.125, "maxX": 317.75, "maxY": 182.125}, "class_id": 0, "box_caption": "Sorrel 0.919", "scores": {"class_score": 0.91943359375}, "domain": "pixel"}, {"position": {"minX": 114.0, "minY": 112.625, "maxX": 211.25, "maxY": 227.375}, "class_id": 0, "box_caption": "Sorrel 0.008", "scores": {"class_score": 0.00844573974609375}, "domain": "pixel"}, {"position": {"minX": 124.625, "minY": 120.5, "maxX": 185.375, "maxY": 211.5}, "class_id": 0, "box_caption": "Sorrel 0.868", "scores": {"class_score": 0.8681640625}, "domain": "pixel"}], "class_labels": {"0": "Sorrel"}}