{"box_data": [{"position": {"minX": 634.0, "minY": 330.25, "maxX": 676.0, "maxY": 386.75}, "class_id": 0, "box_caption": "Sorrel 0.001", "scores": {"class_score": 0.0010776519775390625}, "domain": "pixel"}, {"position": {"minX": 636.5, "minY": 283.5, "maxX": 668.5, "maxY": 376.0}, "class_id": 0, "box_caption": "Sorrel 0.001", "scores": {"class_score": 0.0011510848999023438}, "domain": "pixel"}, {"position": {"minX": 647.0, "minY": 320.75, "maxX": 683.0, "maxY": 371.25}, "class_id": 0, "box_caption": "Sorrel 0.001", "scores": {"class_score": 0.0011243820190429688}, "domain": "pixel"}, {"position": {"minX": 651.5, "minY": 339.5, "maxX": 678.5, "maxY": 373.0}, "class_id": 0, "box_caption": "Sorrel 0.001", "scores": {"class_score": 0.0012302398681640625}, "domain": "pixel"}, {"position": {"minX": 660.5, "minY": 323.5, "maxX": 674.5, "maxY": 392.5}, "class_id": 0, "box_caption": "Sorrel 0.001", "scores": {"class_score": 0.0013303756713867188}, "domain": "pixel"}, {"position": {"minX": 653.0, "minY": 325.0, "maxX": 672.0, "maxY": 390.5}, "class_id": 0, "box_caption": "Sorrel 0.002", "scores": {"class_score": 0.0015544891357421875}, "domain": "pixel"}, {"position": {"minX": 660.5, "minY": 334.0, "maxX": 671.5, "maxY": 386.0}, "class_id": 0, "box_caption": "Sorrel 0.001", "scores": {"class_score": 0.0011606216430664062}, "domain": "pixel"}, {"position": {"minX": 633.5, "minY": 235.0, "maxX": 667.5, "maxY": 361.0}, "class_id": 0, "box_caption": "Sorrel 0.001", "scores": {"class_score": 0.0011739730834960938}, "domain": "pixel"}, {"position": {"minX": 324.5, "minY": 356.5, "maxX": 456.0, "maxY": 385.5}, "class_id": 0, "box_caption": "Sorrel 0.001", "scores": {"class_score": 0.00106048583984375}, "domain": "pixel"}, {"position": {"minX": 349.25, "minY": 373.0, "maxX": 454.75, "maxY": 389.5}, "class_id": 0, "box_caption": "Sorrel 0.001", "scores": {"class_score": 0.001239776611328125}, "domain": "pixel"}, {"position": {"minX": 339.75, "minY": 355.25, "maxX": 430.75, "maxY": 378.25}, "class_id": 0, "box_caption": "Sorrel 0.001", "scores": {"class_score": 0.0011920928955078125}, "domain": "pixel"}, {"position": {"minX": 340.25, "minY": 368.5, "maxX": 435.25, "maxY": 382.0}, "class_id": 0, "box_caption": "Sorrel 0.001", "scores": {"class_score": 0.0010728836059570312}, "domain": "pixel"}, {"position": {"minX": 315.0, "minY": 351.5, "maxX": 413.5, "maxY": 380.5}, "class_id": 0, "box_caption": "Sorrel 0.002", "scores": {"class_score": 0.0018825531005859375}, "domain": "pixel"}, {"position": {"minX": 325.25, "minY": 365.25, "maxX": 426.75, "maxY": 383.75}, "class_id": 0, "box_caption": "Sorrel 0.001", "scores": {"class_score": 0.0010652542114257812}, "domain": "pixel"}, {"position": {"minX": 313.25, "minY": 356.75, "maxX": 397.25, "maxY": 374.25}, "class_id": 0, "box_caption": "Sorrel 0.001", "scores": {"class_score": 0.0011072158813476562}, "domain": "pixel"}, {"position": {"minX": 318.5, "minY": 347.75, "maxX": 365.5, "maxY": 373.75}, "class_id": 0, "box_caption": "Sorrel 0.001", "scores": {"class_score": 0.0012645721435546875}, "domain": "pixel"}, {"position": {"minX": 315.75, "minY": 355.25, "maxX": 361.75, "maxY": 376.25}, "class_id": 0, "box_caption": "Sorrel 0.002", "scores": {"class_score": 0.0020751953125}, "domain": "pixel"}, {"position": {"minX": 328.5, "minY": 353.25, "maxX": 361.5, "maxY": 372.75}, "class_id": 0, "box_caption": "Sorrel 0.001", "scores": {"class_score": 0.0010042190551757812}, "domain": "pixel"}, {"position": {"minX": 324.0, "minY": 356.75, "maxX": 354.5, "maxY": 370.75}, "class_id": 0, "box_caption": "Sorrel 0.002", "scores": {"class_score": 0.0018892288208007812}, "domain": "pixel"}, {"position": {"minX": 324.5, "minY": 348.0, "maxX": 350.5, "maxY": 369.0}, "class_id": 0, "box_caption": "Sorrel 0.001", "scores": {"class_score": 0.0013456344604492188}, "domain": "pixel"}, {"position": {"minX": 313.5, "minY": 347.25, "maxX": 354.0, "maxY": 370.25}, "class_id": 0, "box_caption": "Sorrel 0.001", "scores": {"class_score": 0.0013408660888671875}, "domain": "pixel"}, {"position": {"minX": 155.375, "minY": 374.75, "maxX": 269.0, "maxY": 390.25}, "class_id": 0, "box_caption": "Sorrel 0.001", "scores": {"class_score": 0.001094818115234375}, "domain": "pixel"}, {"position": {"minX": 151.625, "minY": 357.0, "maxX": 242.375, "maxY": 381.0}, "class_id": 0, "box_caption": "Sorrel 0.001", "scores": {"class_score": 0.0010652542114257812}, "domain": "pixel"}, {"position": {"minX": 145.75, "minY": 372.0, "maxX": 245.25, "maxY": 389.0}, "class_id": 0, "box_caption": "Sorrel 0.001", "scores": {"class_score": 0.0013093948364257812}, "domain": "pixel"}, {"position": {"minX": 140.0, "minY": 368.0, "maxX": 243.0, "maxY": 379.5}, "class_id": 0, "box_caption": "Sorrel 0.002", "scores": {"class_score": 0.0016489028930664062}, "domain": "pixel"}, {"position": {"minX": 125.5, "minY": 372.75, "maxX": 205.0, "maxY": 387.75}, "class_id": 0, "box_caption": "Sorrel 0.001", "scores": {"class_score": 0.0011205673217773438}, "domain": "pixel"}, {"position": {"minX": 134.625, "minY": 365.5, "maxX": 193.375, "maxY": 377.0}, "class_id": 0, "box_caption": "Sorrel 0.003", "scores": {"class_score": 0.00254058837890625}, "domain": "pixel"}, {"position": {"minX": 138.125, "minY": 359.25, "maxX": 190.875, "maxY": 374.75}, "class_id": 0, "box_caption": "Sorrel 0.001", "scores": {"class_score": 0.0012645721435546875}, "domain": "pixel"}, {"position": {"minX": 133.25, "minY": 370.5, "maxX": 197.25, "maxY": 384.0}, "class_id": 0, "box_caption": "Sorrel 0.001", "scores": {"class_score": 0.0012063980102539062}, "domain": "pixel"}, {"position": {"minX": 111.6875, "minY": 371.25, "maxX": 189.0, "maxY": 388.75}, "class_id": 0, "box_caption": "Sorrel 0.001", "scores": {"class_score": 0.0010166168212890625}, "domain": "pixel"}, {"position": {"minX": 5.984375, "minY": 372.0, "maxX": 51.3125, "maxY": 384.0}, "class_id": 0, "box_caption": "Sorrel 0.001", "scores": {"class_score": 0.0010166168212890625}, "domain": "pixel"}, {"position": {"minX": -2.390625, "minY": 370.75, "maxX": 41.9375, "maxY": 386.25}, "class_id": 0, "box_caption": "Sorrel 0.001", "scores": {"class_score": 0.0011692047119140625}, "domain": "pixel"}], "class_labels": {"0": "Sorrel"}}