{"box_data": [{"position": {"minX": 565.5, "minY": 0.65625, "maxX": 659.5, "maxY": 18.40625}, "class_id": 0, "box_caption": "Sorrel 0.001", "scores": {"class_score": 0.00127410888671875}, "domain": "pixel"}, {"position": {"minX": 538.0, "minY": 1.25, "maxX": 631.0, "maxY": 19.15625}, "class_id": 0, "box_caption": "Sorrel 0.001", "scores": {"class_score": 0.0013513565063476562}, "domain": "pixel"}, {"position": {"minX": 477.25, "minY": 79.5, "maxX": 602.5, "maxY": 177.5}, "class_id": 0, "box_caption": "Sorrel 0.002", "scores": {"class_score": 0.0018033981323242188}, "domain": "pixel"}, {"position": {"minX": 487.0, "minY": 97.8125, "maxX": 594.0, "maxY": 159.125}, "class_id": 0, "box_caption": "Sorrel 0.009", "scores": {"class_score": 0.009124755859375}, "domain": "pixel"}, {"position": {"minX": 435.5, "minY": 99.125, "maxX": 586.5, "maxY": 203.625}, "class_id": 0, "box_caption": "Sorrel 0.002", "scores": {"class_score": 0.001979827880859375}, "domain": "pixel"}, {"position": {"minX": 473.5, "minY": 0.94921875, "maxX": 561.5, "maxY": 16.734375}, "class_id": 0, "box_caption": "Sorrel 0.001", "scores": {"class_score": 0.0014553070068359375}, "domain": "pixel"}, {"position": {"minX": 437.0, "minY": 98.625, "maxX": 581.5, "maxY": 161.625}, "class_id": 0, "box_caption": "Sorrel 0.001", "scores": {"class_score": 0.0010118484497070312}, "domain": "pixel"}, {"position": {"minX": 380.0, "minY": 99.75, "maxX": 531.0, "maxY": 249.25}, "class_id": 0, "box_caption": "Sorrel 0.002", "scores": {"class_score": 0.0021495819091796875}, "domain": "pixel"}, {"position": {"minX": 414.5, "minY": 169.0, "maxX": 516.0, "maxY": 207.75}, "class_id": 0, "box_caption": "Sorrel 0.001", "scores": {"class_score": 0.0010204315185546875}, "domain": "pixel"}, {"position": {"minX": 414.25, "minY": 111.875, "maxX": 560.5, "maxY": 196.125}, "class_id": 0, "box_caption": "Sorrel 0.013", "scores": {"class_score": 0.01322174072265625}, "domain": "pixel"}, {"position": {"minX": 404.0, "minY": 150.5, "maxX": 506.5, "maxY": 212.25}, "class_id": 0, "box_caption": "Sorrel 0.006", "scores": {"class_score": 0.0063629150390625}, "domain": "pixel"}, {"position": {"minX": 407.25, "minY": 370.5, "maxX": 500.75, "maxY": 384.5}, "class_id": 0, "box_caption": "Sorrel 0.001", "scores": {"class_score": 0.0010366439819335938}, "domain": "pixel"}, {"position": {"minX": 410.75, "minY": 159.75, "maxX": 487.25, "maxY": 201.25}, "class_id": 0, "box_caption": "Sorrel 0.574", "scores": {"class_score": 0.57373046875}, "domain": "pixel"}, {"position": {"minX": 431.0, "minY": 168.25, "maxX": 468.5, "maxY": 187.5}, "class_id": 0, "box_caption": "Sorrel 0.001", "scores": {"class_score": 0.001094818115234375}, "domain": "pixel"}, {"position": {"minX": 427.0, "minY": 163.375, "maxX": 464.0, "maxY": 190.125}, "class_id": 0, "box_caption": "Sorrel 0.003", "scores": {"class_score": 0.0025119781494140625}, "domain": "pixel"}, {"position": {"minX": 371.25, "minY": 370.0, "maxX": 468.25, "maxY": 384.5}, "class_id": 0, "box_caption": "Sorrel 0.001", "scores": {"class_score": 0.00147247314453125}, "domain": "pixel"}, {"position": {"minX": 336.0, "minY": 2.296875, "maxX": 416.0, "maxY": 54.0625}, "class_id": 0, "box_caption": "Sorrel 0.008", "scores": {"class_score": 0.007785797119140625}, "domain": "pixel"}, {"position": {"minX": 338.75, "minY": 10.46875, "maxX": 411.25, "maxY": 42.78125}, "class_id": 0, "box_caption": "Sorrel 0.601", "scores": {"class_score": 0.60107421875}, "domain": "pixel"}, {"position": {"minX": 361.0, "minY": 17.40625, "maxX": 398.5, "maxY": 33.28125}, "class_id": 0, "box_caption": "Sorrel 0.001", "scores": {"class_score": 0.0014896392822265625}, "domain": "pixel"}, {"position": {"minX": 297.25, "minY": 270.25, "maxX": 404.75, "maxY": 363.75}, "class_id": 0, "box_caption": "Sorrel 0.031", "scores": {"class_score": 0.0306243896484375}, "domain": "pixel"}, {"position": {"minX": 355.0, "minY": 14.734375, "maxX": 392.5, "maxY": 30.296875}, "class_id": 0, "box_caption": "Sorrel 0.002", "scores": {"class_score": 0.001956939697265625}, "domain": "pixel"}, {"position": {"minX": 333.25, "minY": 7.5078125, "maxX": 414.25, "maxY": 29.9375}, "class_id": 0, "box_caption": "Sorrel 0.001", "scores": {"class_score": 0.0012645721435546875}, "domain": "pixel"}, {"position": {"minX": 325.0, "minY": 3.390625, "maxX": 403.0, "maxY": 38.625}, "class_id": 0, "box_caption": "Sorrel 0.001", "scores": {"class_score": 0.0012493133544921875}, "domain": "pixel"}, {"position": {"minX": 264.0, "minY": 173.125, "maxX": 416.0, "maxY": 274.25}, "class_id": 0, "box_caption": "Sorrel 0.006", "scores": {"class_score": 0.005512237548828125}, "domain": "pixel"}, {"position": {"minX": 296.25, "minY": 39.9375, "maxX": 385.25, "maxY": 100.4375}, "class_id": 0, "box_caption": "Sorrel 0.005", "scores": {"class_score": 0.004848480224609375}, "domain": "pixel"}, {"position": {"minX": 320.75, "minY": 287.5, "maxX": 382.25, "maxY": 350.0}, "class_id": 0, "box_caption": "Sorrel 0.002", "scores": {"class_score": 0.0022869110107421875}, "domain": "pixel"}, {"position": {"minX": 251.25, "minY": 13.59375, "maxX": 397.25, "maxY": 111.625}, "class_id": 0, "box_caption": "Sorrel 0.005", "scores": {"class_score": 0.005279541015625}, "domain": "pixel"}, {"position": {"minX": 298.0, "minY": 10.9375, "maxX": 404.5, "maxY": 37.625}, "class_id": 0, "box_caption": "Sorrel 0.002", "scores": {"class_score": 0.0017614364624023438}, "domain": "pixel"}, {"position": {"minX": 278.25, "minY": 3.9375, "maxX": 404.25, "maxY": 46.375}, "class_id": 0, "box_caption": "Sorrel 0.019", "scores": {"class_score": 0.0189056396484375}, "domain": "pixel"}, {"position": {"minX": 281.75, "minY": 6.984375, "maxX": 397.25, "maxY": 28.984375}, "class_id": 0, "box_caption": "Sorrel 0.007", "scores": {"class_score": 0.00669097900390625}, "domain": "pixel"}, {"position": {"minX": 307.25, "minY": 50.3125, "maxX": 368.75, "maxY": 94.0625}, "class_id": 0, "box_caption": "Sorrel 0.003", "scores": {"class_score": 0.0029354095458984375}, "domain": "pixel"}, {"position": {"minX": 262.0, "minY": 29.8125, "maxX": 389.0, "maxY": 96.3125}, "class_id": 0, "box_caption": "Sorrel 0.045", "scores": {"class_score": 0.044921875}, "domain": "pixel"}, {"position": {"minX": 271.25, "minY": 179.5, "maxX": 386.25, "maxY": 257.5}, "class_id": 0, "box_caption": "Sorrel 0.012", "scores": {"class_score": 0.01177978515625}, "domain": "pixel"}, {"position": {"minX": 276.25, "minY": 370.0, "maxX": 370.75, "maxY": 384.5}, "class_id": 0, "box_caption": "Sorrel 0.001", "scores": {"class_score": 0.001155853271484375}, "domain": "pixel"}, {"position": {"minX": 269.5, "minY": 18.1875, "maxX": 376.5, "maxY": 83.0625}, "class_id": 0, "box_caption": "Sorrel 0.002", "scores": {"class_score": 0.00243377685546875}, "domain": "pixel"}, {"position": {"minX": 261.5, "minY": 0.5, "maxX": 394.0, "maxY": 32.875}, "class_id": 0, "box_caption": "Sorrel 0.002", "scores": {"class_score": 0.0016613006591796875}, "domain": "pixel"}, {"position": {"minX": 273.5, "minY": 48.5, "maxX": 378.5, "maxY": 94.625}, "class_id": 0, "box_caption": "Sorrel 0.006", "scores": {"class_score": 0.006389617919921875}, "domain": "pixel"}, {"position": {"minX": 263.25, "minY": 1.7890625, "maxX": 364.75, "maxY": 19.25}, "class_id": 0, "box_caption": "Sorrel 0.001", "scores": {"class_score": 0.0010986328125}, "domain": "pixel"}, {"position": {"minX": 260.25, "minY": 10.421875, "maxX": 372.25, "maxY": 55.75}, "class_id": 0, "box_caption": "Sorrel 0.005", "scores": {"class_score": 0.004627227783203125}, "domain": "pixel"}, {"position": {"minX": 246.75, "minY": 370.0, "maxX": 342.25, "maxY": 384.5}, "class_id": 0, "box_caption": "Sorrel 0.002", "scores": {"class_score": 0.0015430450439453125}, "domain": "pixel"}, {"position": {"minX": 259.25, "minY": 17.828125, "maxX": 338.75, "maxY": 62.0625}, "class_id": 0, "box_caption": "Sorrel 0.005", "scores": {"class_score": 0.0048675537109375}, "domain": "pixel"}, {"position": {"minX": 181.5, "minY": -0.7890625, "maxX": 276.25, "maxY": 16.375}, "class_id": 0, "box_caption": "Sorrel 0.001", "scores": {"class_score": 0.0012350082397460938}, "domain": "pixel"}, {"position": {"minX": 29.375, "minY": 293.25, "maxX": 198.125, "maxY": 380.75}, "class_id": 0, "box_caption": "Sorrel 0.001", "scores": {"class_score": 0.001255035400390625}, "domain": "pixel"}, {"position": {"minX": 74.25, "minY": 85.0625, "maxX": 122.625, "maxY": 137.75}, "class_id": 0, "box_caption": "Sorrel 0.007", "scores": {"class_score": 0.007404327392578125}, "domain": "pixel"}, {"position": {"minX": 49.1875, "minY": 296.25, "maxX": 164.75, "maxY": 372.25}, "class_id": 0, "box_caption": "Sorrel 0.005", "scores": {"class_score": 0.005100250244140625}, "domain": "pixel"}, {"position": {"minX": 81.9375, "minY": 91.75, "maxX": 128.5, "maxY": 126.5}, "class_id": 0, "box_caption": "Sorrel 0.002", "scores": {"class_score": 0.0015192031860351562}, "domain": "pixel"}, {"position": {"minX": 86.375, "minY": 89.75, "maxX": 120.125, "maxY": 120.375}, "class_id": 0, "box_caption": "Sorrel 0.002", "scores": {"class_score": 0.0021915435791015625}, "domain": "pixel"}, {"position": {"minX": 68.0625, "minY": 91.875, "maxX": 113.1875, "maxY": 127.75}, "class_id": 0, "box_caption": "Sorrel 0.001", "scores": {"class_score": 0.00147247314453125}, "domain": "pixel"}, {"position": {"minX": -0.2890625, "minY": 361.75, "maxX": 10.1171875, "maxY": 384.75}, "class_id": 0, "box_caption": "Sorrel 0.001", "scores": {"class_score": 0.0011157989501953125}, "domain": "pixel"}], "class_labels": {"0": "Sorrel"}}