{"box_data": [{"position": {"minX": 186.25, "minY": 269.75, "maxX": 280.5, "maxY": 372.75}, "class_id": 0, "box_caption": "Sorrel 0.007", "scores": {"class_score": 0.006877899169921875}, "domain": "pixel"}, {"position": {"minX": 86.875, "minY": 35.5, "maxX": 203.625, "maxY": 117.625}, "class_id": 0, "box_caption": "Sorrel 0.002", "scores": {"class_score": 0.001972198486328125}, "domain": "pixel"}, {"position": {"minX": 42.1875, "minY": 249.5, "maxX": 205.75, "maxY": 363.5}, "class_id": 0, "box_caption": "Sorrel 0.007", "scores": {"class_score": 0.00714874267578125}, "domain": "pixel"}, {"position": {"minX": 94.625, "minY": 327.25, "maxX": 196.375, "maxY": 373.25}, "class_id": 0, "box_caption": "Sorrel 0.002", "scores": {"class_score": 0.0015010833740234375}, "domain": "pixel"}, {"position": {"minX": 64.375, "minY": 323.0, "maxX": 185.125, "maxY": 370.0}, "class_id": 0, "box_caption": "Sorrel 0.001", "scores": {"class_score": 0.0011157989501953125}, "domain": "pixel"}], "class_labels": {"0": "Sorrel"}}