{"box_data": [{"position": {"minX": 159.0, "minY": 268.5, "maxX": 279.5, "maxY": 374.0}, "class_id": 0, "box_caption": "Sorrel 0.077", "scores": {"class_score": 0.07666015625}, "domain": "pixel"}, {"position": {"minX": 88.5625, "minY": 33.5625, "maxX": 204.0, "maxY": 119.4375}, "class_id": 0, "box_caption": "Sorrel 0.004", "scores": {"class_score": 0.003780364990234375}, "domain": "pixel"}, {"position": {"minX": 48.875, "minY": 174.25, "maxX": 212.125, "maxY": 284.25}, "class_id": 0, "box_caption": "Sorrel 0.001", "scores": {"class_score": 0.0010900497436523438}, "domain": "pixel"}, {"position": {"minX": 117.0, "minY": 36.84375, "maxX": 201.0, "maxY": 105.0}, "class_id": 0, "box_caption": "Sorrel 0.003", "scores": {"class_score": 0.0026111602783203125}, "domain": "pixel"}, {"position": {"minX": 112.8125, "minY": 43.375, "maxX": 174.25, "maxY": 104.375}, "class_id": 0, "box_caption": "Sorrel 0.002", "scores": {"class_score": 0.0016489028930664062}, "domain": "pixel"}, {"position": {"minX": -0.4765625, "minY": 309.5, "maxX": 18.21875, "maxY": 382.5}, "class_id": 0, "box_caption": "Sorrel 0.001", "scores": {"class_score": 0.0010166168212890625}, "domain": "pixel"}, {"position": {"minX": -1.0625, "minY": 291.25, "maxX": 14.8125, "maxY": 374.75}, "class_id": 0, "box_caption": "Sorrel 0.001", "scores": {"class_score": 0.0011425018310546875}, "domain": "pixel"}], "class_labels": {"0": "Sorrel"}}