{"box_data": [{"position": {"minX": 204.25, "minY": 280.5, "maxX": 289.25, "maxY": 364.5}, "class_id": 0, "box_caption": "Sorrel 0.001", "scores": {"class_score": 0.0010280609130859375}, "domain": "pixel"}, {"position": {"minX": 189.75, "minY": 266.5, "maxX": 294.5, "maxY": 385.5}, "class_id": 0, "box_caption": "Sorrel 0.004", "scores": {"class_score": 0.004039764404296875}, "domain": "pixel"}, {"position": {"minX": 200.125, "minY": 270.0, "maxX": 272.5, "maxY": 351.5}, "class_id": 0, "box_caption": "Sorrel 0.001", "scores": {"class_score": 0.0011882781982421875}, "domain": "pixel"}, {"position": {"minX": 197.75, "minY": 279.5, "maxX": 260.5, "maxY": 377.0}, "class_id": 0, "box_caption": "Sorrel 0.001", "scores": {"class_score": 0.0012159347534179688}, "domain": "pixel"}, {"position": {"minX": 177.0, "minY": 282.75, "maxX": 279.0, "maxY": 372.75}, "class_id": 0, "box_caption": "Sorrel 0.038", "scores": {"class_score": 0.03790283203125}, "domain": "pixel"}, {"position": {"minX": 143.0, "minY": 293.25, "maxX": 278.75, "maxY": 384.75}, "class_id": 0, "box_caption": "Sorrel 0.002", "scores": {"class_score": 0.0017271041870117188}, "domain": "pixel"}, {"position": {"minX": 147.875, "minY": 313.5, "maxX": 265.0, "maxY": 376.0}, "class_id": 0, "box_caption": "Sorrel 0.004", "scores": {"class_score": 0.004230499267578125}, "domain": "pixel"}, {"position": {"minX": 163.875, "minY": 249.375, "maxX": 207.375, "maxY": 289.75}, "class_id": 0, "box_caption": "Sorrel 0.003", "scores": {"class_score": 0.0029125213623046875}, "domain": "pixel"}, {"position": {"minX": 134.125, "minY": 326.25, "maxX": 243.875, "maxY": 373.25}, "class_id": 0, "box_caption": "Sorrel 0.004", "scores": {"class_score": 0.004150390625}, "domain": "pixel"}, {"position": {"minX": 142.625, "minY": 296.5, "maxX": 238.125, "maxY": 366.0}, "class_id": 0, "box_caption": "Sorrel 0.001", "scores": {"class_score": 0.001220703125}, "domain": "pixel"}, {"position": {"minX": 154.5, "minY": 290.25, "maxX": 208.25, "maxY": 341.25}, "class_id": 0, "box_caption": "Sorrel 0.001", "scores": {"class_score": 0.0012788772583007812}, "domain": "pixel"}, {"position": {"minX": 121.4375, "minY": 335.5, "maxX": 229.0, "maxY": 381.0}, "class_id": 0, "box_caption": "Sorrel 0.008", "scores": {"class_score": 0.00760650634765625}, "domain": "pixel"}, {"position": {"minX": 103.375, "minY": 43.625, "maxX": 212.375, "maxY": 104.375}, "class_id": 0, "box_caption": "Sorrel 0.007", "scores": {"class_score": 0.00661468505859375}, "domain": "pixel"}, {"position": {"minX": 141.625, "minY": 297.25, "maxX": 207.625, "maxY": 350.75}, "class_id": 0, "box_caption": "Sorrel 0.001", "scores": {"class_score": 0.0011377334594726562}, "domain": "pixel"}, {"position": {"minX": 125.625, "minY": 346.25, "maxX": 220.125, "maxY": 376.25}, "class_id": 0, "box_caption": "Sorrel 0.003", "scores": {"class_score": 0.0025615692138671875}, "domain": "pixel"}, {"position": {"minX": 152.75, "minY": 297.0, "maxX": 193.5, "maxY": 331.5}, "class_id": 0, "box_caption": "Sorrel 0.001", "scores": {"class_score": 0.0012941360473632812}, "domain": "pixel"}, {"position": {"minX": 97.0625, "minY": 29.125, "maxX": 225.0, "maxY": 118.125}, "class_id": 0, "box_caption": "Sorrel 0.001", "scores": {"class_score": 0.0010814666748046875}, "domain": "pixel"}, {"position": {"minX": 128.875, "minY": 183.0, "maxX": 181.875, "maxY": 223.5}, "class_id": 0, "box_caption": "Sorrel 0.001", "scores": {"class_score": 0.0011072158813476562}, "domain": "pixel"}, {"position": {"minX": 83.625, "minY": 47.1875, "maxX": 201.125, "maxY": 132.25}, "class_id": 0, "box_caption": "Sorrel 0.001", "scores": {"class_score": 0.0010652542114257812}, "domain": "pixel"}, {"position": {"minX": 67.5, "minY": 42.09375, "maxX": 170.125, "maxY": 126.625}, "class_id": 0, "box_caption": "Sorrel 0.001", "scores": {"class_score": 0.0012302398681640625}, "domain": "pixel"}], "class_labels": {"0": "Sorrel"}}